{"Result":null,"CountryList":null,"StateList":[{"ExtensionData":{},"SehirAdi":"ALABAMA","SehirAdiEn":"ALABAMA","SehirID":"581"},{"ExtensionData":{},"SehirAdi":"ALASKA","SehirAdiEn":"ALASKA","SehirID":"582"},{"ExtensionData":{},"SehirAdi":"ARIZONA","SehirAdiEn":"ARIZONA","SehirID":"583"},{"ExtensionData":{},"SehirAdi":"ARKANSAS","SehirAdiEn":"ARKANSAS","SehirID":"584"},{"ExtensionData":{},"SehirAdi":"CALIFORNIA","SehirAdiEn":"CALIFORNIA","SehirID":"585"},{"ExtensionData":{},"SehirAdi":"CARIBBEAN DENIZI","SehirAdiEn":"CARIBBEAN DENIZI","SehirID":"586"},{"ExtensionData":{},"SehirAdi":"COLORADO","SehirAdiEn":"COLORADO","SehirID":"587"},{"ExtensionData":{},"SehirAdi":"CONNECTICUT","SehirAdiEn":"CONNECTICUT","SehirID":"588"},{"ExtensionData":{},"SehirAdi":"D.C","SehirAdiEn":"D.C","SehirID":"589"},{"ExtensionData":{},"SehirAdi":"DELAWARE","SehirAdiEn":"DELAWARE","SehirID":"590"},{"ExtensionData":{},"SehirAdi":"FLORIDA","SehirAdiEn":"FLORIDA","SehirID":"591"},{"ExtensionData":{},"SehirAdi":"GEORGIA","SehirAdiEn":"GEORGIA","SehirID":"592"},{"ExtensionData":{},"SehirAdi":"HAVAI ADALARI","SehirAdiEn":"HAVAI ADALARI","SehirID":"593"},{"ExtensionData":{},"SehirAdi":"IDAHO","SehirAdiEn":"IDAHO","SehirID":"594"},{"ExtensionData":{},"SehirAdi":"ILLINOIS","SehirAdiEn":"ILLINOIS","SehirID":"595"},{"ExtensionData":{},"SehirAdi":"INDIANA","SehirAdiEn":"INDIANA","SehirID":"596"},{"ExtensionData":{},"SehirAdi":"IOWA","SehirAdiEn":"IOWA","SehirID":"597"},{"ExtensionData":{},"SehirAdi":"KANSAS","SehirAdiEn":"KANSAS","SehirID":"598"},{"ExtensionData":{},"SehirAdi":"KENTUCKY","SehirAdiEn":"KENTUCKY","SehirID":"599"},{"ExtensionData":{},"SehirAdi":"LOUISIANA","SehirAdiEn":"LOUISIANA","SehirID":"600"},{"ExtensionData":{},"SehirAdi":"MAINE","SehirAdiEn":"MAINE","SehirID":"601"},{"ExtensionData":{},"SehirAdi":"MARYLAND","SehirAdiEn":"MARYLAND","SehirID":"602"},{"ExtensionData":{},"SehirAdi":"MASSACHUSETTS","SehirAdiEn":"MASSACHUSETTS","SehirID":"603"},{"ExtensionData":{},"SehirAdi":"MICHIGAN","SehirAdiEn":"MICHIGAN","SehirID":"604"},{"ExtensionData":{},"SehirAdi":"MINNESOTA","SehirAdiEn":"MINNESOTA","SehirID":"605"},{"ExtensionData":{},"SehirAdi":"MISSISSIPPI","SehirAdiEn":"MISSISSIPPI","SehirID":"606"},{"ExtensionData":{},"SehirAdi":"MISSOURI","SehirAdiEn":"MISSOURI","SehirID":"607"},{"ExtensionData":{},"SehirAdi":"MONTANA","SehirAdiEn":"MONTANA","SehirID":"608"},{"ExtensionData":{},"SehirAdi":"NEBRASKA","SehirAdiEn":"NEBRASKA","SehirID":"609"},{"ExtensionData":{},"SehirAdi":"NEVADA","SehirAdiEn":"NEVADA","SehirID":"610"},{"ExtensionData":{},"SehirAdi":"NEW HAMPSHIRE","SehirAdiEn":"NEW HAMPSHIRE","SehirID":"611"},{"ExtensionData":{},"SehirAdi":"NEW JERSEY","SehirAdiEn":"NEW JERSEY","SehirID":"612"},{"ExtensionData":{},"SehirAdi":"NEW MEXICO","SehirAdiEn":"NEW MEXICO","SehirID":"613"},{"ExtensionData":{},"SehirAdi":"NEW YORK","SehirAdiEn":"NEW YORK","SehirID":"614"},{"ExtensionData":{},"SehirAdi":"NORTH CAROLINA","SehirAdiEn":"NORTH CAROLINA","SehirID":"615"},{"ExtensionData":{},"SehirAdi":"NORTH DAKOTA","SehirAdiEn":"NORTH DAKOTA","SehirID":"616"},{"ExtensionData":{},"SehirAdi":"OHIO","SehirAdiEn":"OHIO","SehirID":"617"},{"ExtensionData":{},"SehirAdi":"OKLAHOMA","SehirAdiEn":"OKLAHOMA","SehirID":"618"},{"ExtensionData":{},"SehirAdi":"OREGON","SehirAdiEn":"OREGON","SehirID":"619"},{"ExtensionData":{},"SehirAdi":"PENNSYLVANIA","SehirAdiEn":"PENNSYLVANIA","SehirID":"620"},{"ExtensionData":{},"SehirAdi":"RHODE ISLAND","SehirAdiEn":"RHODE ISLAND","SehirID":"621"},{"ExtensionData":{},"SehirAdi":"SOUTH CAROLINA","SehirAdiEn":"SOUTH CAROLINA","SehirID":"622"},{"ExtensionData":{},"SehirAdi":"SOUTH DAKOTA","SehirAdiEn":"SOUTH DAKOTA","SehirID":"623"},{"ExtensionData":{},"SehirAdi":"TENNESSEE","SehirAdiEn":"TENNESSEE","SehirID":"624"},{"ExtensionData":{},"SehirAdi":"TEXAS","SehirAdiEn":"TEXAS","SehirID":"625"},{"ExtensionData":{},"SehirAdi":"UTAH","SehirAdiEn":"UTAH","SehirID":"626"},{"ExtensionData":{},"SehirAdi":"VERMONT","SehirAdiEn":"VERMONT","SehirID":"627"},{"ExtensionData":{},"SehirAdi":"VIRGINIA","SehirAdiEn":"VIRGINIA","SehirID":"628"},{"ExtensionData":{},"SehirAdi":"WASHINGTON","SehirAdiEn":"WASHINGTON","SehirID":"629"},{"ExtensionData":{},"SehirAdi":"WEST VIRGINIA","SehirAdiEn":"WEST VIRGINIA","SehirID":"630"},{"ExtensionData":{},"SehirAdi":"WISCONSIN","SehirAdiEn":"WISCONSIN","SehirID":"631"},{"ExtensionData":{},"SehirAdi":"WYOMING","SehirAdiEn":"WYOMING","SehirID":"632"}],"StateRegionList":null,"HasStateList":true}