{"Result":null,"CountryList":null,"StateList":[{"ExtensionData":{},"SehirAdi":"ETYOPYA","SehirAdiEn":"ETHIOPIA","SehirID":"697"}],"StateRegionList":[{"IlceUrl":"/tr-TR/19018/adis-ababa-icin-namaz-vakti","ExtensionData":{},"IlceAdi":"ADIS ABABA","IlceAdiEn":"ADIS ABABA","IlceID":"19018"},{"IlceUrl":"/tr-TR/19017/awash-icin-namaz-vakti","ExtensionData":{},"IlceAdi":"AWASH","IlceAdiEn":"AWASH","IlceID":"19017"},{"IlceUrl":"/tr-TR/12798/bahir-dar-icin-namaz-vakti","ExtensionData":{},"IlceAdi":"BAHIR DAR","IlceAdiEn":"BAHIR DAR","IlceID":"12798"},{"IlceUrl":"/tr-TR/12799/dese-icin-namaz-vakti","ExtensionData":{},"IlceAdi":"DESE","IlceAdiEn":"DESE","IlceID":"12799"},{"IlceUrl":"/tr-TR/12800/dire-dawa-icin-namaz-vakti","ExtensionData":{},"IlceAdi":"DIRE DAWA","IlceAdiEn":"DIRE DAWA","IlceID":"12800"},{"IlceUrl":"/tr-TR/12797/gonder-icin-namaz-vakti","ExtensionData":{},"IlceAdi":"GONDER","IlceAdiEn":"GONDER","IlceID":"12797"},{"IlceUrl":"/tr-TR/12801/harer-icin-namaz-vakti","ExtensionData":{},"IlceAdi":"HARER","IlceAdiEn":"HARER","IlceID":"12801"},{"IlceUrl":"/tr-TR/12802/jima-icin-namaz-vakti","ExtensionData":{},"IlceAdi":"JIMA","IlceAdiEn":"JIMA","IlceID":"12802"},{"IlceUrl":"/tr-TR/16736/karakore-icin-namaz-vakti","ExtensionData":{},"IlceAdi":"KARAKORE","IlceAdiEn":"KARAKORE","IlceID":"16736"},{"IlceUrl":"/tr-TR/19019/kombolcha-icin-namaz-vakti","ExtensionData":{},"IlceAdi":"KOMBOLCHA","IlceAdiEn":"KOMBOLCHA","IlceID":"19019"},{"IlceUrl":"/tr-TR/12796/mekele-icin-namaz-vakti","ExtensionData":{},"IlceAdi":"MEKELE","IlceAdiEn":"MEKELE","IlceID":"12796"},{"IlceUrl":"/tr-TR/12795/robitshewa-icin-namaz-vakti","ExtensionData":{},"IlceAdi":"ROBIT(SHEWA)","IlceAdiEn":"ROBIT(SHEWA)","IlceID":"12795"}],"HasStateList":false}