{"Result":null,"CountryList":null,"StateList":[{"ExtensionData":{},"SehirAdi":"MAKEDONYA","SehirAdiEn":"MACEDONIA","SehirID":"765"}],"StateRegionList":[{"IlceUrl":"/tr-TR/15274/berovo-icin-namaz-vakti","ExtensionData":{},"IlceAdi":"BEROVO ","IlceAdiEn":"BEROVO ","IlceID":"15274"},{"IlceUrl":"/tr-TR/15287/blatec-icin-namaz-vakti","ExtensionData":{},"IlceAdi":"BLATEC ","IlceAdiEn":"BLATEC ","IlceID":"15287"},{"IlceUrl":"/tr-TR/15275/bogdanci-icin-namaz-vakti","ExtensionData":{},"IlceAdi":"BOGDANCI","IlceAdiEn":"BOGDANCI","IlceID":"15275"},{"IlceUrl":"/tr-TR/15306/debar-icin-namaz-vakti","ExtensionData":{},"IlceAdi":"DEBAR","IlceAdiEn":"DEBAR","IlceID":"15306"},{"IlceUrl":"/tr-TR/15288/delcevo-icin-namaz-vakti","ExtensionData":{},"IlceAdi":"DELCEVO ","IlceAdiEn":"DELCEVO ","IlceID":"15288"},{"IlceUrl":"/tr-TR/15290/dracevo-icin-namaz-vakti","ExtensionData":{},"IlceAdi":"DRACEVO ","IlceAdiEn":"DRACEVO ","IlceID":"15290"},{"IlceUrl":"/tr-TR/15276/gevgelija-icin-namaz-vakti","ExtensionData":{},"IlceAdi":"GEVGELIJA ","IlceAdiEn":"GEVGELIJA ","IlceID":"15276"},{"IlceUrl":"/tr-TR/15291/gorna-belica-icin-namaz-vakti","ExtensionData":{},"IlceAdi":"GORNA BELICA ","IlceAdiEn":"GORNA BELICA ","IlceID":"15291"},{"IlceUrl":"/tr-TR/15302/gostivar-icin-namaz-vakti","ExtensionData":{},"IlceAdi":"GOSTIVAR","IlceAdiEn":"GOSTIVAR","IlceID":"15302"},{"IlceUrl":"/tr-TR/15292/grupcin-icin-namaz-vakti","ExtensionData":{},"IlceAdi":"GRUPCIN ","IlceAdiEn":"GRUPCIN ","IlceID":"15292"},{"IlceUrl":"/tr-TR/15303/kicevo-icin-namaz-vakti","ExtensionData":{},"IlceAdi":"KICEVO","IlceAdiEn":"KICEVO","IlceID":"15303"},{"IlceUrl":"/tr-TR/15293/kocani-icin-namaz-vakti","ExtensionData":{},"IlceAdi":"KOCANI ","IlceAdiEn":"KOCANI ","IlceID":"15293"},{"IlceUrl":"/tr-TR/15278/konopiste-icin-namaz-vakti","ExtensionData":{},"IlceAdi":"KONOPISTE ","IlceAdiEn":"KONOPISTE ","IlceID":"15278"},{"IlceUrl":"/tr-TR/15294/kratovo-icin-namaz-vakti","ExtensionData":{},"IlceAdi":"KRATOVO","IlceAdiEn":"KRATOVO","IlceID":"15294"},{"IlceUrl":"/tr-TR/15295/kriva-palanka-icin-namaz-vakti","ExtensionData":{},"IlceAdi":"KRIVA PALANKA ","IlceAdiEn":"KRIVA PALANKA ","IlceID":"15295"},{"IlceUrl":"/tr-TR/15279/krivogastani-icin-namaz-vakti","ExtensionData":{},"IlceAdi":"KRIVOGASTANI ","IlceAdiEn":"KRIVOGASTANI ","IlceID":"15279"},{"IlceUrl":"/tr-TR/15300/kumanovo-icin-namaz-vakti","ExtensionData":{},"IlceAdi":"KUMANOVO","IlceAdiEn":"KUMANOVO","IlceID":"15300"},{"IlceUrl":"/tr-TR/15299/manastirbitola-icin-namaz-vakti","ExtensionData":{},"IlceAdi":"MANASTIR(bitola)","IlceAdiEn":"MANASTIR(bitola)","IlceID":"15299"},{"IlceUrl":"/tr-TR/15280/negotino-gostivar-icin-namaz-vakti","ExtensionData":{},"IlceAdi":"NEGOTINO (Gostivar)","IlceAdiEn":"NEGOTINO (Gostivar)","IlceID":"15280"},{"IlceUrl":"/tr-TR/15281/negotino-kavadarci-icin-namaz-vakti","ExtensionData":{},"IlceAdi":"NEGOTINO (Kavadarci)","IlceAdiEn":"NEGOTINO (Kavadarci)","IlceID":"15281"},{"IlceUrl":"/tr-TR/15305/ohrid-icin-namaz-vakti","ExtensionData":{},"IlceAdi":"OHRID","IlceAdiEn":"OHRID","IlceID":"15305"},{"IlceUrl":"/tr-TR/15296/orizari-icin-namaz-vakti","ExtensionData":{},"IlceAdi":"ORIZARI ","IlceAdiEn":"ORIZARI ","IlceID":"15296"},{"IlceUrl":"/tr-TR/15307/prilep-icin-namaz-vakti","ExtensionData":{},"IlceAdi":"PRILEP","IlceAdiEn":"PRILEP","IlceID":"15307"},{"IlceUrl":"/tr-TR/15282/radovis-icin-namaz-vakti","ExtensionData":{},"IlceAdi":"RADOVIS ","IlceAdiEn":"RADOVIS ","IlceID":"15282"},{"IlceUrl":"/tr-TR/15283/resen-icin-namaz-vakti","ExtensionData":{},"IlceAdi":"RESEN ","IlceAdiEn":"RESEN ","IlceID":"15283"},{"IlceUrl":"/tr-TR/15284/ropotovo-icin-namaz-vakti","ExtensionData":{},"IlceAdi":"ROPOTOVO ","IlceAdiEn":"ROPOTOVO ","IlceID":"15284"},{"IlceUrl":"/tr-TR/15297/sopiste-icin-namaz-vakti","ExtensionData":{},"IlceAdi":"SOPISTE","IlceAdiEn":"SOPISTE","IlceID":"15297"},{"IlceUrl":"/tr-TR/15308/stip-icin-namaz-vakti","ExtensionData":{},"IlceAdi":"STIP","IlceAdiEn":"STIP","IlceID":"15308"},{"IlceUrl":"/tr-TR/15304/struga-icin-namaz-vakti","ExtensionData":{},"IlceAdi":"STRUGA","IlceAdiEn":"STRUGA","IlceID":"15304"},{"IlceUrl":"/tr-TR/15285/strumica-icin-namaz-vakti","ExtensionData":{},"IlceAdi":"STRUMICA ","IlceAdiEn":"STRUMICA ","IlceID":"15285"},{"IlceUrl":"/tr-TR/15289/tearce-icin-namaz-vakti","ExtensionData":{},"IlceAdi":"TEARCE","IlceAdiEn":"TEARCE","IlceID":"15289"},{"IlceUrl":"/tr-TR/15301/tetovo-icin-namaz-vakti","ExtensionData":{},"IlceAdi":"TETOVO","IlceAdiEn":"TETOVO","IlceID":"15301"},{"IlceUrl":"/tr-TR/15309/titov-veles-icin-namaz-vakti","ExtensionData":{},"IlceAdi":"TITOV VELES","IlceAdiEn":"TITOV VELES","IlceID":"15309"},{"IlceUrl":"/tr-TR/15298/uskup-icin-namaz-vakti","ExtensionData":{},"IlceAdi":"USKUP","IlceAdiEn":"SKOPJE","IlceID":"15298"},{"IlceUrl":"/tr-TR/15286/valandovo-icin-namaz-vakti","ExtensionData":{},"IlceAdi":"VALANDOVO ","IlceAdiEn":"VALANDOVO ","IlceID":"15286"}],"HasStateList":false}