{"Result":null,"CountryList":null,"StateList":[{"ExtensionData":{},"SehirAdi":"LIBYA","SehirAdiEn":"LIBYA","SehirID":"757"}],"StateRegionList":[{"IlceUrl":"/tr-TR/15188/al-bayda-icin-namaz-vakti","ExtensionData":{},"IlceAdi":"AL BAYDA","IlceAdiEn":"AL BAYDA","IlceID":"15188"},{"IlceUrl":"/tr-TR/15183/al-khums-icin-namaz-vakti","ExtensionData":{},"IlceAdi":"AL KHUMS","IlceAdiEn":"AL KHUMS","IlceID":"15183"},{"IlceUrl":"/tr-TR/15185/awbari-icin-namaz-vakti","ExtensionData":{},"IlceAdi":"AWBARI","IlceAdiEn":"AWBARI","IlceID":"15185"},{"IlceUrl":"/tr-TR/15190/bingazi-icin-namaz-vakti","ExtensionData":{},"IlceAdi":"BINGAZI","IlceAdiEn":"BINGAZI","IlceID":"15190"},{"IlceUrl":"/tr-TR/15189/ghat-icin-namaz-vakti","ExtensionData":{},"IlceAdi":"GHAT","IlceAdiEn":"GHAT","IlceID":"15189"},{"IlceUrl":"/tr-TR/15182/misratah-icin-namaz-vakti","ExtensionData":{},"IlceAdi":"MISRATAH","IlceAdiEn":"MISRATAH","IlceID":"15182"},{"IlceUrl":"/tr-TR/15186/murzuq-icin-namaz-vakti","ExtensionData":{},"IlceAdi":"MURZUQ","IlceAdiEn":"MURZUQ","IlceID":"15186"},{"IlceUrl":"/tr-TR/15184/sabha-icin-namaz-vakti","ExtensionData":{},"IlceAdi":"SABHA","IlceAdiEn":"SABHA","IlceID":"15184"},{"IlceUrl":"/tr-TR/15187/tobruk-icin-namaz-vakti","ExtensionData":{},"IlceAdi":"TOBRUK","IlceAdiEn":"TOBRUK","IlceID":"15187"},{"IlceUrl":"/tr-TR/15191/tripoli-icin-namaz-vakti","ExtensionData":{},"IlceAdi":"TRIPOLI","IlceAdiEn":"TRIPOLI","IlceID":"15191"},{"IlceUrl":"/tr-TR/15181/zuwarah-icin-namaz-vakti","ExtensionData":{},"IlceAdi":"ZUWARAH","IlceAdiEn":"ZUWARAH","IlceID":"15181"}],"HasStateList":false}